{
    "id":"Bkci_8qcdvQ",
    "created_at":"2016-06-01T19:13:24-04:00",
    "updated_at":"2021-07-07T04:00:46-04:00",
    "promoted_at":"2016-06-01T19:13:24-04:00",
    "width":5760,
    "height":3840,
    "color":"#26260c",
    "blur_hash":"LXCZ^kjEMwNG.ARjjEj[Mwflxuj]",
    "description":"Wet mountain valley",
    "alt_description":"green mountain across body of water",
    "urls":{
        "raw":"https://images.unsplash.com/photo-1464822759023-fed622ff2c3b?ixid=MnwyNDUwMTl8MHwxfHJhbmRvbXx8fHx8fHx8fDE2MjU2NzM5MDk&ixlib=rb-1.2.1",
        "full":"https://images.unsplash.com/photo-1464822759023-fed622ff2c3b?crop=entropy&cs=srgb&fm=jpg&ixid=MnwyNDUwMTl8MHwxfHJhbmRvbXx8fHx8fHx8fDE2MjU2NzM5MDk&ixlib=rb-1.2.1&q=85",
        "regular":"https://images.unsplash.com/photo-1464822759023-fed622ff2c3b?crop=entropy&cs=tinysrgb&fit=max&fm=jpg&ixid=MnwyNDUwMTl8MHwxfHJhbmRvbXx8fHx8fHx8fDE2MjU2NzM5MDk&ixlib=rb-1.2.1&q=80&w=1080",
        "small":"https://images.unsplash.com/photo-1464822759023-fed622ff2c3b?crop=entropy&cs=tinysrgb&fit=max&fm=jpg&ixid=MnwyNDUwMTl8MHwxfHJhbmRvbXx8fHx8fHx8fDE2MjU2NzM5MDk&ixlib=rb-1.2.1&q=80&w=400",
        "thumb":"https://images.unsplash.com/photo-1464822759023-fed622ff2c3b?crop=entropy&cs=tinysrgb&fit=max&fm=jpg&ixid=MnwyNDUwMTl8MHwxfHJhbmRvbXx8fHx8fHx8fDE2MjU2NzM5MDk&ixlib=rb-1.2.1&q=80&w=200"
    },
    "links":{
        "self":"https://api.unsplash.com/photos/Bkci_8qcdvQ",
        "html":"https://unsplash.com/photos/Bkci_8qcdvQ",
        "download":"https://unsplash.com/photos/Bkci_8qcdvQ/download",
        "download_location":"https://api.unsplash.com/photos/Bkci_8qcdvQ/download?ixid=MnwyNDUwMTl8MHwxfHJhbmRvbXx8fHx8fHx8fDE2MjU2NzM5MDk"
    },
    "categories":[
        
    ],
    "likes":4694,
    "liked_by_user":false,
    "current_user_collections":[
        
    ],
    "sponsorship":"None",
    "user":{
        "id":"j7YsMEZljNw",
        "updated_at":"2021-07-07T06:26:40-04:00",
        "username":"kalenemsley",
        "name":"Kalen Emsley",
        "first_name":"Kalen",
        "last_name":"Emsley",
        "twitter_username":"None",
        "portfolio_url":"http://www.instagram.com/kalenemsley",
        "bio":"None",
        "location":"Vancouver",
        "links":{
            "self":"https://api.unsplash.com/users/kalenemsley",
            "html":"https://unsplash.com/@kalenemsley",
            "photos":"https://api.unsplash.com/users/kalenemsley/photos",
            "likes":"https://api.unsplash.com/users/kalenemsley/likes",
            "portfolio":"https://api.unsplash.com/users/kalenemsley/portfolio",
            "following":"https://api.unsplash.com/users/kalenemsley/following",
            "followers":"https://api.unsplash.com/users/kalenemsley/followers"
        },
        "profile_image":{
            "small":"https://images.unsplash.com/profile-fb-1463693385-fdbd53826943.jpg?ixlib=rb-1.2.1&q=80&fm=jpg&crop=faces&cs=tinysrgb&fit=crop&h=32&w=32",
            "medium":"https://images.unsplash.com/profile-fb-1463693385-fdbd53826943.jpg?ixlib=rb-1.2.1&q=80&fm=jpg&crop=faces&cs=tinysrgb&fit=crop&h=64&w=64",
            "large":"https://images.unsplash.com/profile-fb-1463693385-fdbd53826943.jpg?ixlib=rb-1.2.1&q=80&fm=jpg&crop=faces&cs=tinysrgb&fit=crop&h=128&w=128"
        },
        "instagram_username":"kalenemsley",
        "total_collections":0,
        "total_likes":10,
        "total_photos":26,
        "accepted_tos":true,
        "for_hire":true,
        "social":{
            "instagram_username":"kalenemsley",
            "portfolio_url":"http://www.instagram.com/kalenemsley",
            "twitter_username":"None"
        }
    },
    "exif":{
        "make":"Canon",
        "model":"Canon EOS 5D Mark III",
        "exposure_time":"1/200",
        "aperture":"22.0",
        "focal_length":"50.0",
        "iso":640
    },
    "location":{
        "title":"Kluane National Park and Reserve of Canada, Canada",
        "name":"Kluane National Park and Reserve of Canada, Canada",
        "city":"None",
        "country":"Canada",
        "position":{
            "latitude":60.75,
            "longitude":-139.5
        }
    },
    "views":70047507,
    "downloads":571754
}